ref_fetch.py
ref_fetch-0.3.1.dist-info/licenses/LICENSE
ref_fetch-0.3.1.dist-info/METADATA
ref_fetch-0.3.1.dist-info/WHEEL
ref_fetch-0.3.1.dist-info/entry_points.txt
ref_fetch-0.3.1.dist-info/top_level.txt
ref_fetch-0.3.1.dist-info/RECORD
