Metadata-Version: 2.4
Name: ref-fetch
Version: 0.3.1
Summary: Automates fetching and caching of documentation and source code for specified versions of core standard libraries and third-party packages. It intelligently locates repositories, resolves dependencies, and provides a local, version-controlled reference of your project's entire dependency tree for LLM-assisted development.
Author-email: roobert <roobert@gmail.com>
License: MIT
Project-URL: Homepage, https://github.com/roobert/ref-fetch
Classifier: Programming Language :: Python :: 3
Classifier: Operating System :: OS Independent
Requires-Python: >=3.9
License-File: LICENSE
Requires-Dist: PyYAML
Requires-Dist: requests
Requires-Dist: ddgs
Requires-Dist: tomli
Requires-Dist: beautifulsoup4
Requires-Dist: rich
Dynamic: license-file
